bulkdnsquery.py
bulkdnsquery-1.0.0.dist-info/LICENSE
bulkdnsquery-1.0.0.dist-info/METADATA
bulkdnsquery-1.0.0.dist-info/WHEEL
bulkdnsquery-1.0.0.dist-info/entry_points.txt
bulkdnsquery-1.0.0.dist-info/top_level.txt
bulkdnsquery-1.0.0.dist-info/RECORD
