Metadata-Version: 2.2
Name: bulkdnsquery
Version: 1.0.0
Summary: Bulk DNS Query Tool
License: MIT
Project-URL: repository, https://github.com/pfptcommunity/bulkdnsquery
Requires-Python: >3.9
License-File: LICENSE
Requires-Dist: xlsxwriter
Requires-Dist: dnspython
